Workbook
Name a: SIMULADOR!$D$13
Name aporte: SIMULADOR!$D$9
Name patrimonio: SIMULADOR!$D$12
Name qtd_anos: SIMULADOR!$D$10
Name rendimento_carteira: SIMULADOR!$D$5
Name taxa_mensal: SIMULADOR!$D$11

Sheet SIMULADOR
A1: SIMULADOR DE INVESTIMENTOS EM FUNDOS IMOBILIÁRIOS
B3: CONFIGURAÇÕES
B4: Salário | D4: 2000
B5: Rendimento Carteira | D5: 0.006
B6: Sugestão de Investimento (30%) | D6: =D4*30% -> 600
B8: INVESTIMENTO MENSAL
B9: Quanto investir por mês ? | D9: 200
B10: Por Quantos Anos ? | D10: 5
B11: Taxa de Rendimento mensal ? | D11: 0.0108
B12: Patrimônio acumulado ? | D12: =FV(taxa_mensal,qtd_anos*12,aporte*-1) -> 16760.804
B13: Dividendos Mensais ? | D13: {=patrimonio*rendimento_carteira} -> 100.56482
B15: Cenários | D15: Dividendo
A16: 2 | B16: Quanto em 2 Anos ? | C16: =FV($D$11,$A16*12,$D$9*-1) -> 5446.1727 | D16: =C16*rendimento_carteira -> 32.677036
A17: 5 | B17: Quanto em 5 Anos ? | C17: =FV($D$11,$A17*12,$D$9*-1) -> 16760.804 | D17: =C17*rendimento_carteira -> 100.56482
A18: 10 | B18: Quanto em 10 Anos ? | C18: =FV($D$11,$A18*12,$D$9*-1) -> 48691.533 | D18: =C18*rendimento_carteira -> 292.1492
A19: 20 | B19: Quanto em 20 Anos ? | C19: =FV($D$11,$A19*12,$D$9*-1) -> 225409.8 | D19: =C19*rendimento_carteira -> 1352.4588
A20: 30 | B20: Quanto em 30 Anos ? | C20: =FV($D$11,$A20*12,$D$9*-1) -> 866780.96 | D20: =C20*rendimento_carteira -> 5200.6858
B23: PERFIL | C23: Agressivo
B24: VALOR A SER INVESTIDO POR MÊS | C24: =aporte -> 200
B26: TIPO DE FII | C26: Percentual Sugerido | D26: Valores
B27: PAPEL | C27: =_xlfn.XLOOKUP($C$23&"-"&B27,Planilha2!B:B,Planilha2!E:E) -> 0.5 | D27: =C27*$C$24 -> 100
B28: TIJOLO | C28: =_xlfn.XLOOKUP($C$23&"-"&B28,Planilha2!B:B,Planilha2!E:E) -> 0.1 | D28: =C28*$C$24 -> 20
B29: HÍBRIDOS | C29: =_xlfn.XLOOKUP($C$23&"-"&B29,Planilha2!B:B,Planilha2!E:E) -> 0.05 | D29: =C29*$C$24 -> 10
B30: FOFs | C30: =_xlfn.XLOOKUP($C$23&"-"&B30,Planilha2!B:B,Planilha2!E:E) -> 0.05 | D30: =C30*$C$24 -> 10
B31: DESENVOLVIMENTO | C31: =_xlfn.XLOOKUP($C$23&"-"&B31,Planilha2!B:B,Planilha2!E:E) -> 0.2 | D31: =C31*$C$24 -> 40
B32: HOTELARIAS | C32: =_xlfn.XLOOKUP($C$23&"-"&B32,Planilha2!B:B,Planilha2!E:E) -> 0.1 | D32: =C32*$C$24 -> 20
D33: =SUM(D27:D32) -> 200

Sheet Planilha2
B2: CHAVE | C2: PERFIL | D2: TIPO DE FII | E2: %
B3: =C3&"-"&D3 -> Conservador-PAPEL | C3: Conservador | D3: PAPEL | E3: 0.3
B4: =C4&"-"&D4 -> Conservador-TIJOLO | C4: Conservador | D4: TIJOLO | E4: 0.5
B5: =C5&"-"&D5 -> Conservador-HÍBRIDOS | C5: Conservador | D5: HÍBRIDOS | E5: 0.1
B6: =C6&"-"&D6 -> Conservador-FOFs | C6: Conservador | D6: FOFs | E6: 0.1
B7: =C7&"-"&D7 -> Conservador-DESENVOLVIMENTO | C7: Conservador | D7: DESENVOLVIMENTO | E7: 0
B8: =C8&"-"&D8 -> Conservador-HOTELARIAS | C8: Conservador | D8: HOTELARIAS | E8: 0
B9: =C9&"-"&D9 -> Moderado-PAPEL | C9: Moderado | D9: PAPEL | E9: 0.32
B10: =C10&"-"&D10 -> Moderado-TIJOLO | C10: Moderado | D10: TIJOLO | E10: 0.35
B11: =C11&"-"&D11 -> Moderado-HÍBRIDOS | C11: Moderado | D11: HÍBRIDOS | E11: 0.08
B12: =C12&"-"&D12 -> Moderado-FOFs | C12: Moderado | D12: FOFs | E12: 0.05
B13: =C13&"-"&D13 -> Moderado-DESENVOLVIMENTO | C13: Moderado | D13: DESENVOLVIMENTO | E13: 0.1
B14: =C14&"-"&D14 -> Moderado-HOTELARIAS | C14: Moderado | D14: HOTELARIAS | E14: 0.1
... B20: =C20&"-"&D20 -> Agressivo-HOTELARIAS | C20: Agressivo | D20: HOTELARIAS | E20: 0.1
